main.py
setup.py
BabetMF.egg-info/PKG-INFO
BabetMF.egg-info/SOURCES.txt
BabetMF.egg-info/dependency_links.txt
BabetMF.egg-info/requires.txt
BabetMF.egg-info/top_level.txt